LICENSE.txt
README.md
setup.cfg
setup.py
django_rtk_later/__init__.py
django_rtk_later/admin.py
django_rtk_later/apps.py
django_rtk_later/backends.py
django_rtk_later/models.py
django_rtk_later/validators.py
django_rtk_later.egg-info/PKG-INFO
django_rtk_later.egg-info/SOURCES.txt
django_rtk_later.egg-info/dependency_links.txt
django_rtk_later.egg-info/not-zip-safe
django_rtk_later.egg-info/requires.txt
django_rtk_later.egg-info/top_level.txt
django_rtk_later/migrations/0001_initial.py
django_rtk_later/migrations/__init__.py
django_rtk_later/mutations/__init__.py
django_rtk_later/mutations/activateaccount.py
django_rtk_later/mutations/registeraccount.py
django_rtk_later/queries/__init__.py
django_rtk_later/utils/__init__.py
django_rtk_later/utils/create_user.py