Metadata-Version: 2.1
Name: django-rtk-later
Version: 0.4.0
Summary: Extension of django-rtk that requires a password in the activation step
Home-page: https://github.com/mnieber/django-rtk-home/blob/main/django-rtk-later/README.md
Author: Maarten Nieber
Author-email: hallomaarten@yahoo.com
License: MIT
Platform: UNKNOWN
Requires-Python: >=3.6
